dbapi2abc/__init__.py
dbapi2abc/dbapi2abc.py
dbapi2abc-1.1.3.dist-info/METADATA
dbapi2abc-1.1.3.dist-info/WHEEL
dbapi2abc-1.1.3.dist-info/top_level.txt
dbapi2abc-1.1.3.dist-info/RECORD
