Metadata-Version: 2.1
Name: dbapi2abc
Version: 1.1.3
Summary: Provide an Abstract Base Class for PEP249 compliant databases
Home-page: https://github.com/campbsb/dbapi2abc
Author: Steve Campbell
License: UNKNOWN
Project-URL: Bug Reports, https://github.com/campbsb/dbapi2abc/issues
Project-URL: Say Thanks!, https://saythanks.io/to/campbsb
Project-URL: Source, https://github.com/campbsb/dbapi2abc/
Keywords: PEP249,Database,Database API
Platform: UNKNOWN
Classifier: Development Status :: 4 - Beta
Classifier: Intended Audience :: Developers
Classifier: Topic :: Database
Classifier: Typing :: Typed
Classifier: License :: OSI Approved :: Apache Software License
Classifier: Programming Language :: Python :: 3
Requires-Python: >=3.5, <4
